py_ard-1.5.5.data/scripts/pyard
py_ard-1.5.5.data/scripts/pyard-import
py_ard-1.5.5.data/scripts/pyard-reduce-csv
py_ard-1.5.5.data/scripts/pyard-status
pyard/CWD2.csv
pyard/__init__.py
pyard/ard.py
pyard/blender.py
pyard/constants.py
pyard/data_repository.py
pyard/db.py
pyard/dna_relshp.csv
pyard/drbx.py
pyard/exceptions.py
pyard/load.py
pyard/mappings.py
pyard/misc.py
pyard/serology.py
pyard/smart_sort.py
py_ard-1.5.5.dist-info/COPYING
py_ard-1.5.5.dist-info/LICENSE
py_ard-1.5.5.dist-info/METADATA
py_ard-1.5.5.dist-info/WHEEL
py_ard-1.5.5.dist-info/top_level.txt
py_ard-1.5.5.dist-info/RECORD
