Metadata-Version: 2.1
Name: py-ard
Version: 1.5.5
Summary: ARD reduction for HLA with Python
Home-page: https://github.com/nmdp-bioinformatics/py-ard
Author: CIBMTR
Author-email: cibmtr-pypi@nmdp.org
License: LGPL 3.0
Keywords: pyard
Platform: UNKNOWN
Classifier: Development Status :: 5 - Production/Stable
Classifier: Intended Audience :: Science/Research
Classifier: Topic :: Scientific/Engineering :: Bio-Informatics
Classifier: License :: OSI Approved :: GNU Lesser General Public License v3 (LGPLv3)
Classifier: Natural Language :: English
Classifier: Programming Language :: Python :: 3.9
Classifier: Programming Language :: Python :: 3.10
Classifier: Programming Language :: Python :: 3.11
Classifier: Programming Language :: Python :: 3.12
Provides: pyard
License-File: LICENSE
License-File: COPYING
Requires-Dist: setuptools==78.1.1
Requires-Dist: toml==0.10.2
Requires-Dist: numpy==2.0.2
Requires-Dist: pandas==2.2.2
